onegov.election_day-3.13.9-py3.6-nspkg.pth
onegov/election_day/.gitignore
onegov/election_day/__init__.py
onegov/election_day/app.py
onegov/election_day/cli.py
onegov/election_day/directives.py
onegov/election_day/path.py
onegov/election_day/pdf.py
onegov/election_day/upgrade.py
onegov/election_day/assets/css/jquery.datetimepicker.css
onegov/election_day/assets/css/tablesaw.css
onegov/election_day/assets/js/charts-init.js
onegov/election_day/assets/js/common.js
onegov/election_day/assets/js/d3.chart.bar.js
onegov/election_day/assets/js/d3.chart.grouped.js
onegov/election_day/assets/js/d3.chart.sankey.js
onegov/election_day/assets/js/d3.js
onegov/election_day/assets/js/d3.map.districts.js
onegov/election_day/assets/js/d3.map.entities.js
onegov/election_day/assets/js/d3.sankey.js
onegov/election_day/assets/js/d3.tip.js
onegov/election_day/assets/js/datetimepicker.js
onegov/election_day/assets/js/embed.js
onegov/election_day/assets/js/foundation.js
onegov/election_day/assets/js/iframeResizer.contentWindow.js
onegov/election_day/assets/js/jquery.datetimepicker.js
onegov/election_day/assets/js/jquery.js
onegov/election_day/assets/js/jquery.tablesorter.js
onegov/election_day/assets/js/jquery.tablesorter.staticRow.js
onegov/election_day/assets/js/modernizr.js
onegov/election_day/assets/js/tablesaw-init.js
onegov/election_day/assets/js/tablesaw.jquery.js
onegov/election_day/assets/js/topojson.js
onegov/election_day/assets/js/underscore.js
onegov/election_day/assets/js/__tests__/__snapshots__/d3.chart.bar.js.snap
onegov/election_day/assets/js/__tests__/__snapshots__/d3.chart.grouped.js.snap
onegov/election_day/assets/js/__tests__/__snapshots__/d3.chart.sankey.js.snap
onegov/election_day/assets/js/__tests__/__snapshots__/d3.map.districts.js.snap
onegov/election_day/assets/js/__tests__/__snapshots__/d3.map.entities.js.snap
onegov/election_day/collections/__init__.py
onegov/election_day/collections/archived_results.py
onegov/election_day/collections/data_sources.py
onegov.election_day-3.13.9.dist-info/METADATA
onegov.election_day-3.13.9.dist-info/WHEEL
onegov.election_day-3.13.9.dist-info/entry_points.txt
onegov.election_day-3.13.9.dist-info/namespace_packages.txt
onegov.election_day-3.13.9.dist-info/top_level.txt
onegov.election_day-3.13.9.dist-info/RECORD
